cross_transformers_pytorch/__init__.py
cross_transformers_pytorch/cross_transformers_pytorch.py
cross_transformers_pytorch-0.0.2.dist-info/LICENSE
cross_transformers_pytorch-0.0.2.dist-info/METADATA
cross_transformers_pytorch-0.0.2.dist-info/WHEEL
cross_transformers_pytorch-0.0.2.dist-info/top_level.txt
cross_transformers_pytorch-0.0.2.dist-info/RECORD
